LICENSE.txt
README.rst
setup.cfg
setup.py
cos202finalbycharawi/__init__.py
cos202finalbycharawi/module.py
cos202finalbycharawi.egg-info/PKG-INFO
cos202finalbycharawi.egg-info/SOURCES.txt
cos202finalbycharawi.egg-info/dependency_links.txt
cos202finalbycharawi.egg-info/top_level.txt