Metadata-Version: 2.1
Name: cos202finalbycharawi
Version: 0.0.3
Summary: vectors and points by Charawi Detphumi
Home-page: https://github.com/ShabiiPam/cos202finalbycharawi
Download-URL: https://github.com/ShabiiPam/cos202finalbycharawi/archive/v0.0.1.zip
Author: Charawi Detphumi
Author-email: partgirlcharawi@gmail.com
License: MIT
Keywords: Point,Mathematics,Vector,Charawi
Classifier: Development Status :: 3 - Alpha
Classifier: Intended Audience :: Education
Classifier: Topic :: Utilities
Classifier: License :: OSI Approved :: MIT License
Classifier: Programming Language :: Python :: 3
Classifier: Programming Language :: Python :: 3.4
Classifier: Programming Language :: Python :: 3.5
Classifier: Programming Language :: Python :: 3.6
Classifier: Programming Language :: Python :: 3.7
Classifier: Programming Language :: Python :: 3.8
Classifier: Programming Language :: Python :: 3.9
Classifier: Programming Language :: Python :: 3.10
License-File: LICENSE.txt
